csc_cia_stne/__init__.py
csc_cia_stne/bc_correios.py
csc_cia_stne/bc_sta.py
csc_cia_stne/email.py
csc_cia_stne/ftp.py
csc_cia_stne/gcp_bigquery.py
csc_cia_stne/gcp_bucket.py
csc_cia_stne/gcp_document_ai.py
csc_cia_stne/google_drive.py
csc_cia_stne/jerry.py
csc_cia_stne/karavela.py
csc_cia_stne/logger_json.py
csc_cia_stne/logger_rich.py
csc_cia_stne/provio.py
csc_cia_stne/servicenow.py
csc_cia_stne/slack.py
csc_cia_stne/stne_admin.py
csc_cia_stne/wacess.py
csc_cia_stne/web.py
csc_cia_stne/utilitarios/__init__.py
csc_cia_stne/utilitarios/functions/__init__.py
csc_cia_stne/utilitarios/functions/func_b64.py
csc_cia_stne/utilitarios/functions/func_converters.py
csc_cia_stne/utilitarios/functions/func_datetime.py
csc_cia_stne/utilitarios/functions/func_delete.py
csc_cia_stne/utilitarios/functions/func_get_secret.py
csc_cia_stne/utilitarios/functions/func_pdf_extract.py
csc_cia_stne/utilitarios/functions/func_recriar_pastas.py
csc_cia_stne/utilitarios/functions/func_settings.py
csc_cia_stne/utilitarios/functions/func_titulo.py
csc_cia_stne/utilitarios/functions/func_validate_json.py
csc_cia_stne/utilitarios/validations/GcpBigQueryValidator.py
csc_cia_stne/utilitarios/validations/GoogleDriveValidator.py
csc_cia_stne/utilitarios/validations/ServiceNowValidator.py
csc_cia_stne/utilitarios/validations/__init__.py
csc_cia_stne/utilitarios/validations/ftp.py
csc_cia_stne/utilitarios/validations/gcp_bucket.py
csc_cia_stne/utilitarios/validations/waccess.py
csc_cia_stne/utilitarios/validations/web_validator.py
csc_cia_stne/utilitarios/web_screen/__init__.py
csc_cia_stne/utilitarios/web_screen/web_screen_abstract.py
csc_cia_stne/utilitarios/web_screen/web_screen_botcity.py
csc_cia_stne/utilitarios/web_screen/web_screen_selenium.py
csc_cia_stne-0.1.68.dist-info/licenses/LICENCE
csc_cia_stne-0.1.68.dist-info/METADATA
csc_cia_stne-0.1.68.dist-info/WHEEL
csc_cia_stne-0.1.68.dist-info/top_level.txt
csc_cia_stne-0.1.68.dist-info/RECORD
