Metadata-Version: 2.4
Name: csc_cia_stne
Version: 0.1.68
Summary: Biblioteca do time CSC-CIA utilizada no desenvolvimento de RPAs
License: MIT
Keywords: karavela,csc,cia,stone,rpa,botcity,stne
License-File: LICENCE
Requires-Dist: setuptools
Requires-Dist: tzdata
Requires-Dist: python-json-logger
Requires-Dist: rich
Requires-Dist: requests
Requires-Dist: pydantic
Requires-Dist: pydantic_settings
Requires-Dist: zeep
Requires-Dist: google-cloud-bigquery
Requires-Dist: google-cloud-storage
Requires-Dist: google-cloud-bigquery-storage
Requires-Dist: google-auth
Requires-Dist: google-auth-oauthlib
Requires-Dist: google-auth-httplib2
Requires-Dist: google-api-python-client
Requires-Dist: google-cloud-documentai
Requires-Dist: pyjwt
Requires-Dist: PyYAML
Requires-Dist: python-dotenv
Requires-Dist: slack_sdk
Requires-Dist: webdriver-manager
Requires-Dist: botcity-framework-core
Requires-Dist: botcity-framework-web
Requires-Dist: email-validator
Requires-Dist: botcity-maestro-sdk
Requires-Dist: psutil
Requires-Dist: cryptography
Requires-Dist: PyPDF2
Requires-Dist: pypdf
Requires-Dist: pycryptodome
Requires-Dist: openai
Requires-Dist: pycurl
Dynamic: license-file
